TheWayToFlaskZhongwenban/README.md
TheWayToFlaskZhongwenban/__init__.py
TheWayToFlaskZhongwenban/__main__.py
TheWayToFlaskZhongwenban/file.epub
TheWayToFlaskZhongwenban/index.html
TheWayToFlaskZhongwenban/css/__init__.py
TheWayToFlaskZhongwenban/css/annotations.css
TheWayToFlaskZhongwenban/css/main.css
TheWayToFlaskZhongwenban/css/normalize.css
TheWayToFlaskZhongwenban/css/popup.css
TheWayToFlaskZhongwenban/font/__init__.py
TheWayToFlaskZhongwenban/font/fontello.eot
TheWayToFlaskZhongwenban/font/fontello.svg
TheWayToFlaskZhongwenban/font/fontello.ttf
TheWayToFlaskZhongwenban/font/fontello.woff
TheWayToFlaskZhongwenban/img/__init__.py
TheWayToFlaskZhongwenban/img/annotator-glyph-sprite.png
TheWayToFlaskZhongwenban/img/annotator-icon-sprite.png
TheWayToFlaskZhongwenban/img/apple-touch-icon.png
TheWayToFlaskZhongwenban/img/cancelfullscreen.png
TheWayToFlaskZhongwenban/img/close.png
TheWayToFlaskZhongwenban/img/fullscreen.png
TheWayToFlaskZhongwenban/img/loader.gif
TheWayToFlaskZhongwenban/img/menu-icon.png
TheWayToFlaskZhongwenban/img/save.png
TheWayToFlaskZhongwenban/img/saved.png
TheWayToFlaskZhongwenban/img/settings-s.png
TheWayToFlaskZhongwenban/img/settings.png
TheWayToFlaskZhongwenban/img/star.png
TheWayToFlaskZhongwenban/js/__init__.py
TheWayToFlaskZhongwenban/js/epub.js
TheWayToFlaskZhongwenban/js/epub.min.js
TheWayToFlaskZhongwenban/js/epub.min.map
TheWayToFlaskZhongwenban/js/hooks.min.js
TheWayToFlaskZhongwenban/js/hooks.min.map
TheWayToFlaskZhongwenban/js/reader.js
TheWayToFlaskZhongwenban/js/reader.js.map
TheWayToFlaskZhongwenban/js/reader.min.js
TheWayToFlaskZhongwenban/js/reader.min.map
TheWayToFlaskZhongwenban/js/hooks/__init__.py
TheWayToFlaskZhongwenban/js/hooks/extensions/__init__.py
TheWayToFlaskZhongwenban/js/hooks/extensions/highlight.js
TheWayToFlaskZhongwenban/js/libs/__init__.py
TheWayToFlaskZhongwenban/js/libs/jquery.min.js
TheWayToFlaskZhongwenban/js/libs/localforage.min.js
TheWayToFlaskZhongwenban/js/libs/screenfull.js
the_way_to_flask_zhongwenban-2024.3.3.0.dist-info/METADATA
the_way_to_flask_zhongwenban-2024.3.3.0.dist-info/WHEEL
the_way_to_flask_zhongwenban-2024.3.3.0.dist-info/entry_points.txt
the_way_to_flask_zhongwenban-2024.3.3.0.dist-info/top_level.txt
the_way_to_flask_zhongwenban-2024.3.3.0.dist-info/RECORD
